purewind/__init__.py
purewind/purewind.py
purewind-0.1.1.dist-info/METADATA
purewind-0.1.1.dist-info/WHEEL
purewind-0.1.1.dist-info/entry_points.txt
purewind-0.1.1.dist-info/top_level.txt
purewind-0.1.1.dist-info/RECORD
