Metadata-Version: 2.4
Name: purewind
Version: 0.1.1
Summary: A tiny windowing wrapper built on WIN-32 api
Author-email: winddowned <none@gmail.com>
License: MIT
Keywords: window,win32,graphics,purewind
Classifier: Programming Language :: Python :: 3
Classifier: Programming Language :: Python :: 3 :: Only
Classifier: Operating System :: Microsoft :: Windows
Classifier: License :: OSI Approved :: MIT License
Requires-Python: >=3.8
Provides-Extra: dev
Requires-Dist: black; extra == "dev"
Requires-Dist: flake8; extra == "dev"
Requires-Dist: pytest>=7.0; extra == "dev"
